{
  "file_path": "d:\\Navgurukul\\data\\enterprise_dataset\\documents\\notes\\Reinforcement_Learning_Lecture_02.txt",
  "file_type": ".txt",
  "processed_at": "2026-01-17T13:52:43.237545",
  "metadata": {
    "file_path": "d:\\Navgurukul\\data\\enterprise_dataset\\documents\\notes\\Reinforcement_Learning_Lecture_02.txt",
    "file_type": ".txt",
    "file_size": 2531,
    "processed_at": "2026-01-17T13:52:42.977328",
    "content_hash": "f19fa29f8ac3378fb7780ce6cd6686ffb3d8a851a2ab46e6216f6d36b96ac394",
    "language": null,
    "page_count": null,
    "duration": null,
    "word_count": 321,
    "metadata": {
      "line_count": 85,
      "is_markdown": false
    }
  },
  "summary": "",
  "topics": [
    "Iteration",
    "Value",
    "Value Iteration",
    "Lecture",
    "Learning"
  ],
  "key_concepts": [
    "iteration",
    "value",
    "value iteration",
    "lecture",
    "learning",
    "real",
    "reinforcement",
    "reinforcement learning",
    "implement",
    "iteration optimal",
    "iteration optimal policies",
    "optimal",
    "optimal policies",
    "policies",
    "policy"
  ],
  "entity_count": 69,
  "word_count": 321,
  "flashcards": [],
  "quiz_questions": [],
  "knowledge_graph": {
    "statistics": {
      "node_count": 22,
      "edge_count": 186,
      "density": 0.8051948051948052,
      "is_connected": true,
      "diameter": 2,
      "average_shortest_path_length": 1.1948051948051948,
      "average_clustering": 0.922077922077922,
      "most_central_concepts": [
        [
          "iteration",
          1.0
        ],
        [
          "value",
          1.0
        ],
        [
          "value iteration",
          1.0
        ],
        [
          "lecture",
          1.0
        ],
        [
          "implementation",
          1.0
        ],
        [
          "implement",
          1.0
        ],
        [
          "real",
          1.0
        ],
        [
          "applications",
          1.0
        ],
        [
          "dynamic",
          0.7619047619047619
        ],
        [
          "dynamic programming",
          0.7619047619047619
        ]
      ]
    },
    "learning_paths": [
      [
        "iteration",
        "value"
      ],
      [
        "iteration",
        "value iteration"
      ],
      [
        "iteration",
        "lecture"
      ],
      [
        "iteration",
        "implementation"
      ]
    ],
    "output_directory": "outputs\\knowledge_graphs\\Reinforcement_Learning_Lecture_02"
  },
  "rag_document_id": "a966602a-bccd-441f-8192-e039506bffce",
  "processing_time_seconds": 0.494885
}